eqi_analysis/__init__.py
eqi_analysis/_version.py
eqi_analysis/admin/__init__.py
eqi_analysis/admin/scrape.py
eqi_analysis/admin/transform.py
eqi_analysis/core/__init__.py
eqi_analysis/core/analysis.py
eqi_analysis/core/extension.py
eqi_analysis/core/plot.py
eqi_analysis/core/refdata.py
eqi_analysis/core/utils.py
eqi_analysis/core/wrapper.py
eqi_analysis/core/db/__init__.py
eqi_analysis/core/db/analysis.py
eqi_analysis/core/entity/__init__.py
eqi_analysis/core/entity/access.py
eqi_analysis/core/entity/connection.py
eqi_analysis/core/entity/entity.py
eqi_analysis/meta/__init__.py
eqi_analysis/meta/linkup.py
eqi_analysis/meta/sesamm.py
eqi_analysis/model/__init__.py
eqi_analysis/model/soc_local.py
eqi_analysis/model/soc_spark.py
eqi_analysis-1.1.0.dist-info/METADATA
eqi_analysis-1.1.0.dist-info/RECORD
eqi_analysis-1.1.0.dist-info/WHEEL
eqi_analysis-1.1.0.dist-info/top_level.txt
tests/__init__.py
tests/test_analysis.py
tests/test_analysis_int.py
tests/test_eqidf.py
tests/test_refdata_int.py
tests/test_scrape.py
