Metadata-Version: 2.1
Name: eqi-analysis
Version: 1.1.0
Summary: Factor analysis package for EQI project.
Home-page: https://github.com/jinzha098718/eqi-analysis
Author: Jinpeng Zhang
Author-email: jinzha098718@gmail.com
License: MIT
Platform: UNKNOWN
Classifier: Programming Language :: Python :: 3.6
Classifier: License :: OSI Approved :: MIT License
Classifier: Operating System :: OS Independent
Requires-Dist: eqi-utils (>=1.0.3)
Requires-Dist: pandas (>=0.23.3)
Requires-Dist: cx-Oracle (>=6.0b2)
Requires-Dist: sqlalchemy (>=1.2.8)
Requires-Dist: alphalens-eqi (>=1.1.0)
Requires-Dist: matplotlib (>=2.2.2)
Requires-Dist: numpy (>=1.14.5)
